{"name":"t:sections.footer.name","type":"footer","sections":{"footer":{"type":"footer","blocks":{"text_jRpznx":{"type":"text","settings":{"heading":"Heading","subtext":"<p>Share contact information, store details, and brand content with your customers.<\/p><p>Share contact information, store details, and brand content with your customers.<\/p><p>Share contact information, store details, and brand content with your customers.<\/p><p>Share contact information, store details, and brand content with your customers.<\/p><p>Share contact information, store details, and brand content with your customers.<\/p>"}},"footer-0":{"type":"link_list","settings":{"heading":"","menu":"elwood-footer"}},"link_list_Jy9fBA":{"type":"link_list","settings":{"heading":"Quick links","menu":"elwood-footer"}},"link_list_eLUr9M":{"type":"link_list","settings":{"heading":"Quick links","menu":"elwood-footer"}}},"block_order":["text_jRpznx","footer-0","link_list_Jy9fBA","link_list_eLUr9M"],"settings":{"color_scheme":"scheme-5","newsletter_enable":true,"newsletter_heading":"SIGN UP FOR OUR NEWSLETTER","enable_follow_on_shop":true,"show_social":true,"enable_country_selector":true,"enable_language_selector":true,"payment_enable":true,"show_policy":true,"margin_top":0,"padding_top":20,"padding_bottom":0}}},"order":["footer"]}